<?xml version="1.0" encoding="utf-8" ?>
<dwsync>
<file name="uo.jpg" server="C:/wamp/www/e-millenium/" local="131239639508562306" remote="131239639500000000" />
<file name="uk.jpg" server="C:/wamp/www/e-millenium/" local="131239648620767839" remote="131239648620000000" />
<file name="upb.jpg" server="C:/wamp/www/e-millenium/" local="131239650167627274" remote="131239650160000000" />
<file name="usta.png" server="C:/wamp/www/e-millenium/" local="131239652306630813" remote="131239652300000000" />
<file name="uan.jpg" server="C:/wamp/www/e-millenium/" local="131239645038689390" remote="131239645030000000" />
<file name="upo.jpg" server="C:/wamp/www/e-millenium/" local="131239662416833863" remote="131239662410000000" />
<file name="ucao.gif" server="C:/wamp/www/e-millenium/" local="131239658537674917" remote="131239658530000000" />
<file name="iam.png" server="C:/wamp/www/e-millenium/" local="131239661078153243" remote="131239661070000000" />
<file name="uo2.jpg" server="C:/wamp/www/e-millenium/" local="131239666349309336" remote="131239666340000000" />
</dwsync>